Workbook
Name aporte: 'Simulador Fundo_Investimentos'!$E$17:$E$17
Name div_mensais: 'Simulador Fundo_Investimentos'!$E$21:$E$21
Name patrimonio: 'Simulador Fundo_Investimentos'!$E$20:$E$20
Name rend_carteira: 'Simulador Fundo_Investimentos'!$E$12:$E$12
Name rend_mensal: 'Simulador Fundo_Investimentos'!$E$19:$E$19
Name salario: 'Simulador Fundo_Investimentos'!$E$11:$E$11
Name sug_inves: 'Simulador Fundo_Investimentos'!$E$13:$E$13
Name tempo: 'Simulador Fundo_Investimentos'!$E$18:$E$18

Sheet Simulador Fundo_Investimentos
B10: CONFIGURAÇÕES
B11: Salário | E11: 5000
B12: Rendimento Carteira | E12: 0.006
B13: Sugestão de Investimento | E13: =E11*30% -> 1500
B15: INVESTIMENTO MENSAL
B17: Quanto investir por mês? | E17: 500
B18: Por quantos anos? | E18: 5
B19: Taxa de rendimento mensal? | E19: 0.01079
B20: Patrimônio acumulado? | E20: {=FV(rend_mensal,tempo*12,aporte*-1)} -> 41888.457
B21: Dividendos mensais? | E21: {=patrimonio*rend_carteira} -> 251.33074
B23: Cenários | E23: Dividendo
A24: 2 | B24: Quanto em 2 anos? | D24: =FV($E$19,$A$24*12,$E$17*-1) -> 13613.814 | E24: {=D24*rend_carteira} -> 81.682882
A25: 5 | B25: Quanto em 5 anos? | D25: =FV($E$19,$A$25*12,$E$17*-1) -> 41888.457 | E25: {=D25*rend_carteira} -> 251.33074
A26: 10 | B26: Quanto em 10 anos? | D26: =FV($E$19,$A$26*12,$E$17*-1) -> 121642.11 | E26: {=D26*rend_carteira} -> 729.85264
A27: 20 | B27: Quanto em 20 anos? | D27: =FV($E$19,$A$27*12,$E$17*-1) -> 562599.2 | E27: {=D27*rend_carteira} -> 3375.5952
A28: 30 | B28: Quanto em 30 anos? | D28: =FV($E$19,$A$28*12,$E$17*-1) -> 2161084.8 | E28: {=D28*rend_carteira} -> 12966.509
B29: 5
B30: PERFIL | E30: Agressivo
B31: VALOR A SER INVESTIDO POR MÊS | E31: {=aporte} -> 500
B33: TIPO DE FII | D33: PERCENTUAL SUGERIDO | E33: VALORES
B34: PAPEL | D34: =VLOOKUP($E$30&"-"&B34,Tabela_Apoio!$A:$D,4,FALSE) -> 0.5 | E34: =$E$31*D34 -> 250
B35: TIJOLO | D35: =VLOOKUP($E$30&"-"&B35,Tabela_Apoio!$A:$D,4,FALSE) -> 0.1 | E35: =$E$31*D35 -> 50
B36: HÍBRIDOS | D36: =VLOOKUP($E$30&"-"&B36,Tabela_Apoio!$A:$D,4,FALSE) -> 0.05 | E36: =$E$31*D36 -> 25
B37: FOFs | D37: =VLOOKUP($E$30&"-"&B37,Tabela_Apoio!$A:$D,4,FALSE) -> 0.05 | E37: =$E$31*D37 -> 25
B38: DESENVOLVIMENTO | D38: =VLOOKUP($E$30&"-"&B38,Tabela_Apoio!$A:$D,4,FALSE) -> 0.2 | E38: =$E$31*D38 -> 100
B39: HOTELARIAS | D39: =VLOOKUP($E$30&"-"&B39,Tabela_Apoio!$A:$D,4,FALSE) -> 0.1 | E39: =$E$31*D39 -> 50
E40: =SUM(E34:E39) -> 500
B44: 10
B45: 20
B46: 30

Sheet Tabela_Apoio
A2: CHAVE COMPOSTA | B2: PERFIL | C2: TIPO DE FII | D2: PERCENTUAL SUGERIDO
A3: =$B$3&"-"&C3 -> CONSERVADOR-PAPEL | B3: CONSERVADOR | C3: PAPEL | D3: 0.3
A4: =$B$3&"-"&C4 -> CONSERVADOR-TIJOLO | B4: CONSERVADOR | C4: TIJOLO | D4: 0.5
A5: =$B$3&"-"&C5 -> CONSERVADOR-HÍBRIDOS | B5: CONSERVADOR | C5: HÍBRIDOS | D5: 0.1
A6: =$B$3&"-"&C6 -> CONSERVADOR-FOFs | B6: CONSERVADOR | C6: FOFs | D6: 0.1
A7: =$B$3&"-"&C7 -> CONSERVADOR-DESENVOLVIMENTO | B7: CONSERVADOR | C7: DESENVOLVIMENTO | D7: 0
A8: =$B$3&"-"&C8 -> CONSERVADOR-HOTELARIAS | B8: CONSERVADOR | C8: HOTELARIAS | D8: 0
A9: =$B$9&"-"&C9 -> MODERADO-PAPEL | B9: MODERADO | C9: PAPEL | D9: 0.32
A10: =$B$9&"-"&C10 -> MODERADO-TIJOLO | B10: MODERADO | C10: TIJOLO | D10: 0.35
A11: =$B$9&"-"&C11 -> MODERADO-HÍBRIDOS | B11: MODERADO | C11: HÍBRIDOS | D11: 0.08
A12: =$B$9&"-"&C12 -> MODERADO-FOFs | B12: MODERADO | C12: FOFs | D12: 0.05
A13: =$B$9&"-"&C13 -> MODERADO-DESENVOLVIMENTO | B13: MODERADO | C13: DESENVOLVIMENTO | D13: 0.1
A14: =$B$9&"-"&C14 -> MODERADO-HOTELARIAS | B14: MODERADO | C14: HOTELARIAS | D14: 0.1
A15: =$B$15&"-"&C15 -> AGRESSIVO-PAPEL | B15: AGRESSIVO | C15: PAPEL | D15: 0.5
A16: =$B$15&"-"&C16 -> AGRESSIVO-TIJOLO | B16: AGRESSIVO | C16: TIJOLO | D16: 0.1
A17: =$B$15&"-"&C17 -> AGRESSIVO-HÍBRIDOS | B17: AGRESSIVO | C17: HÍBRIDOS | D17: 0.05
A18: =$B$15&"-"&C18 -> AGRESSIVO-FOFs | B18: AGRESSIVO | C18: FOFs | D18: 0.05
A19: =$B$15&"-"&C19 -> AGRESSIVO-DESENVOLVIMENTO | B19: AGRESSIVO | C19: DESENVOLVIMENTO | D19: 0.2
A20: =$B$15&"-"&C20 -> AGRESSIVO-HOTELARIAS | B20: AGRESSIVO | C20: HOTELARIAS | D20: 0.1
